MANIFEST.in
README.rst
setup.cfg
setup.py
evenz/__init__.py
evenz/events.py
evenz/version.py
evenz.egg-info/PKG-INFO
evenz.egg-info/SOURCES.txt
evenz.egg-info/dependency_links.txt
evenz.egg-info/requires.txt
evenz.egg-info/top_level.txt