Metadata-Version: 1.2
Name: evenz
Version: 0.1.0
Summary: Simplify event-driven python!
Home-page: https://github.com/patdaburu/evenz
Author: Pat Daburu
Author-email: pat@daburu.net
License: MIT
Download-URL: https://github.com/patdaburu/evenz/archive/0.1.0.tar.gz
Platform: UNKNOWN
Classifier: Development Status :: 3 - Alpha
Classifier: Intended Audience :: Developers
Classifier: Topic :: Software Development :: Libraries
Classifier: License :: OSI Approved :: MIT License
Classifier: Programming Language :: Python :: 3.6
Requires-Python: >=0.0.1
